<?xml version="1.0" encoding="utf-8"?>
<cms.pagetemplate>
  <PageTemplateCategoryID>
    <CodeName>Events</CodeName>
    <GUID>9b24a425-4b22-494c-a07b-e400c371ce79</GUID>
    <ObjectType>cms.pagetemplatecategory</ObjectType>
  </PageTemplateCategoryID>
  <PageTemplateCloneAsAdHoc>False</PageTemplateCloneAsAdHoc>
  <PageTemplateCodeName>cms.eventcalendarwithdetails</PageTemplateCodeName>
  <PageTemplateDescription>
    <![CDATA[Calendar displaying events for selected months with event details.]]>
  </PageTemplateDescription>
  <PageTemplateDisplayName>Event calendar with event details</PageTemplateDisplayName>
  <PageTemplateFile />
  <PageTemplateGUID>d52c92e0-5a0e-4643-8a2e-697f13f7a4df</PageTemplateGUID>
  <PageTemplateHeader />
  <PageTemplateIconClass>icon-l-calendar-number-article</PageTemplateIconClass>
  <PageTemplateInheritPageLevels>/{0}</PageTemplateInheritPageLevels>
  <PageTemplateIsReusable>True</PageTemplateIsReusable>
  <PageTemplateLayout>
<![CDATA[
<!-- Container -->
<div class="eventCalendarDetail">
	<!-- Top zone -->
	<div class="zoneTop">
		<cms:CMSWebPartZone ZoneID="zoneTop" runat="server" />      
	</div>
	<!-- Left zone -->
	<div class="zoneLeft" style="float: left;">
	      <cms:CMSWebPartZone ZoneID="zoneLeft" runat="server" />      
	</div>	
	<!-- Right zone -->
	<div class="zoneRight" style="float: right;">
      		<cms:CMSWebPartZone ZoneID="zoneRight" runat="server" />      
	</div>
</div>

]]>
  </PageTemplateLayout>
  <PageTemplateShowAsMasterTemplate>False</PageTemplateShowAsMasterTemplate>
  <PageTemplateType>portal</PageTemplateType>
  <PageTemplateWebParts>
    <page>
      <webpartzone id="zoneLeft">
        <properties>
          <property name="disableviewstate">False</property>
          <property name="hideonsubpages">False</property>
          <property name="timezonetype">inherit</property>
          <property name="useupdatepanel">False</property>
          <property name="visible">True</property>
        </properties>
        <webpart controlid="EventCalendar" guid="ae223ac3-9cb7-4119-97f8-60801600b776" type="EventCalendar" v="1">
          <property name="cachedependencies">
<![CDATA[
##DEFAULT##

]]>
          </property>
          <property name="cacheitemname"></property>
          <property name="cacheminutes"></property>
          <property name="cat_open_ajax"></property>
          <property name="cat_open_output_filter"></property>
          <property name="cat_open_performance"></property>
          <property name="cat_open_time zones">True</property>
          <property name="cat_open_visibility"></property>
          <property name="checkpermissions">False</property>
          <property name="classnames">cms.bookingevent</property>
          <property name="columns"></property>
          <property name="combinewithdefaultculture"></property>
          <property name="container"></property>
          <property name="containercssclass"></property>
          <property name="containercustomcontent"></property>
          <property name="containerhideonsubpages">False</property>
          <property name="containertitle"></property>
          <property name="contentafter"></property>
          <property name="contentbefore"></property>
          <property name="controlid">EventCalendar</property>
          <property name="culturecode"></property>
          <property name="customtimezone">CentralAmerica</property>
          <property name="dayfield">EventDate</property>
          <property name="disablemacros">False</property>
          <property name="disableviewstate">False</property>
          <property name="displaytoroles"></property>
          <property name="enableoutputfilter">False</property>
          <property name="eventdetailtransformation">CMS.BookingEvent.CalendarEvent</property>
          <property name="eventendfield">EventEndDate</property>
          <property name="filtername"></property>
          <property name="hidedefaultdaynumber">False</property>
          <property name="hideonsubpages">False</property>
          <property name="instanceguid">ae223ac3-9cb7-4119-97f8-60801600b776</property>
          <property name="maxrelativelevel">-1</property>
          <property name="noeventtransformationname">CMS.BookingEvent.CalendarNoEvent</property>
          <property name="orderby"></property>
          <property name="outputconverttablestodivs">none</property>
          <property name="outputfixattributes">True</property>
          <property name="outputfixhtml5">True</property>
          <property name="outputfixjavascript">True</property>
          <property name="outputfixlowercase">True</property>
          <property name="outputfixselfclose">True</property>
          <property name="outputfixtags">True</property>
          <property name="outputresolveurls">True</property>
          <property name="partialcachedependencies">
<![CDATA[
##DEFAULT##

]]>
          </property>
          <property name="partialcacheminutes"></property>
          <property name="path">/calendar/%</property>
          <property name="relatednodeisontheleftside">False</property>
          <property name="relationshipname">isrelatedto</property>
          <property name="relationshipwithnodeguid">00000000-0000-0000-0000-000000000000</property>
          <property name="selectonlypublished">True</property>
          <property name="showfordocumenttypes"></property>
          <property name="sitename"></property>
          <property name="skinid"></property>
          <property name="timezonetype">custom</property>
          <property name="transformationname">CMS.BookingEvent.CalendarEvent</property>
          <property name="useupdatepanel">False</property>
          <property name="visible">True</property>
          <property name="webparttitle"></property>
          <property name="webparttype">EventCalendar</property>
          <property name="wherecondition"></property>
        </webpart>
        <webpart controlid="EventRegistration" guid="1fc785bf-294e-4da1-8da3-d929a9ca17bd" type="EventRegistration" v="1">
          <property name="allowanonymousregistration">True</property>
          <property name="allowexporttooutlook">False</property>
          <property name="cat_open_ajax"></property>
          <property name="cat_open_output_filter"></property>
          <property name="cat_open_performance"></property>
          <property name="cat_open_time zones"></property>
          <property name="cat_open_visibility"></property>
          <property name="container">BlackBox</property>
          <property name="containercssclass"></property>
          <property name="containercustomcontent"></property>
          <property name="containerhideonsubpages">False</property>
          <property name="containertitle"></property>
          <property name="contentafter"></property>
          <property name="contentbefore"></property>
          <property name="controlid">EventRegistration</property>
          <property name="customtimezone"></property>
          <property name="disablemacros">False</property>
          <property name="disableviewstate">False</property>
          <property name="displaytoroles"></property>
          <property name="enableoutputfilter">False</property>
          <property name="hideonsubpages">False</property>
          <property name="instanceguid">1fc785bf-294e-4da1-8da3-d929a9ca17bd</property>
          <property name="outputconverttablestodivs">none</property>
          <property name="outputfixattributes">True</property>
          <property name="outputfixhtml5">True</property>
          <property name="outputfixjavascript">True</property>
          <property name="outputfixlowercase">True</property>
          <property name="outputfixselfclose">True</property>
          <property name="outputresolveurls">True</property>
          <property name="partialcachedependencies">
<![CDATA[
##DEFAULT##

]]>
          </property>
          <property name="partialcacheminutes"></property>
          <property name="preservepartialcacheonpostback">False</property>
          <property name="registrationtitle">Registration</property>
          <property name="requirename">True</property>
          <property name="requirephone">False</property>
          <property name="showfordocumenttypes"></property>
          <property name="timezonetype">inherit</property>
          <property name="useupdatepanel">False</property>
          <property name="visible">True</property>
          <property name="webparttitle"></property>
          <property name="webparttype">EventRegistration</property>
        </webpart>
        <webpart controlid="MessageBoard" guid="495f15ca-4270-45b7-aa46-48723f345467" type="MessageBoard" v="1">
          <property name="allowemptyrating">True</property>
          <property name="boardaccess">0</property>
          <property name="boardbaseurl"></property>
          <property name="boarddisplayname"></property>
          <property name="boardenablesubscriptions">False</property>
          <property name="boardmoderated">False</property>
          <property name="boardmoderators"></property>
          <property name="boardopened">True</property>
          <property name="boardopenedfrom"></property>
          <property name="boardopenedto"></property>
          <property name="boardowner">document</property>
          <property name="boardrequireemails">False</property>
          <property name="boardroles"></property>
          <property name="boardunsubscriptionurl"></property>
          <property name="boardusecaptcha">False</property>
          <property name="cachedependencies">
<![CDATA[
##DEFAULT##

]]>
          </property>
          <property name="cacheitemname"></property>
          <property name="cacheminutes"></property>
          <property name="cat_open_ajax"></property>
          <property name="cat_open_output_filter"></property>
          <property name="cat_open_performance"></property>
          <property name="cat_open_time zones"></property>
          <property name="cat_open_visibility"></property>
          <property name="checkifuserrated">False</property>
          <property name="checkpermissions">False</property>
          <property name="container"></property>
          <property name="containercssclass"></property>
          <property name="containercustomcontent"></property>
          <property name="containerhideonsubpages">False</property>
          <property name="containertitle"></property>
          <property name="contentafter"></property>
          <property name="contentbefore"></property>
          <property name="controlid">MessageBoard</property>
          <property name="customtimezone"></property>
          <property name="disablemacros">False</property>
          <property name="disableviewstate">False</property>
          <property name="displaytoroles"></property>
          <property name="enableanonymousread">True</property>
          <property name="enablecontentrating">False</property>
          <property name="enableoutputfilter">False</property>
          <property name="hideonsubpages">False</property>
          <property name="instanceguid">495f15ca-4270-45b7-aa46-48723f345467</property>
          <property name="logactivity">True</property>
          <property name="maxratingvalue">5</property>
          <property name="messagetransformation">Community.Transformations.MessageBoard</property>
          <property name="nomessagestext"></property>
          <property name="orderby"></property>
          <property name="outputconverttablestodivs">none</property>
          <property name="outputfixattributes">True</property>
          <property name="outputfixhtml5">True</property>
          <property name="outputfixjavascript">True</property>
          <property name="outputfixlowercase">True</property>
          <property name="outputfixselfclose">True</property>
          <property name="outputresolveurls">True</property>
          <property name="partialcachedependencies">
<![CDATA[
##DEFAULT##

]]>
          </property>
          <property name="partialcacheminutes"></property>
          <property name="preservepartialcacheonpostback">False</property>
          <property name="ratingtype">DropDown</property>
          <property name="showapprove">True</property>
          <property name="showdelete">True</property>
          <property name="showedit">True</property>
          <property name="showemailfield">True</property>
          <property name="showfordocumenttypes"></property>
          <property name="shownamefield">True</property>
          <property name="showreject">True</property>
          <property name="showurlfield">True</property>
          <property name="timezonetype">inherit</property>
          <property name="useupdatepanel">False</property>
          <property name="visible">True</property>
          <property name="webparttitle"></property>
          <property name="webparttype">MessageBoard</property>
        </webpart>
        <webpart controlid="ContributionList" guid="4328d023-26c4-47b6-990e-79e73d1a72dc" type="ContributionList" v="1">
          <property name="allowdelete">True</property>
          <property name="allowedchildclasses"></property>
          <property name="allowedit">True</property>
          <property name="allowinsert">True</property>
          <property name="allowusers">0</property>
          <property name="alternativeformname"></property>
          <property name="cat_open_ajax"></property>
          <property name="cat_open_output_filter"></property>
          <property name="cat_open_performance"></property>
          <property name="cat_open_time zones"></property>
          <property name="cat_open_visibility"></property>
          <property name="checkdocpermissionsforinsert">True</property>
          <property name="checkpermissions">False</property>
          <property name="classnames"></property>
          <property name="columns"></property>
          <property name="combinewithdefaultculture"></property>
          <property name="container"></property>
          <property name="containercssclass"></property>
          <property name="containercustomcontent"></property>
          <property name="containerhideonsubpages">False</property>
          <property name="containertitle"></property>
          <property name="contentafter"></property>
          <property name="contentbefore"></property>
          <property name="controlid">ContributionList</property>
          <property name="culturecode"></property>
          <property name="customtimezone"></property>
          <property name="disablemacros">False</property>
          <property name="disableviewstate">False</property>
          <property name="displaylist">True</property>
          <property name="displaytoroles"></property>
          <property name="enableoutputfilter">False</property>
          <property name="hideonsubpages">False</property>
          <property name="instanceguid">4328d023-26c4-47b6-990e-79e73d1a72dc</property>
          <property name="listbuttontext"></property>
          <property name="logactivity">True</property>
          <property name="maxrelativelevel">-1</property>
          <property name="newdocumentpath"></property>
          <property name="newitembuttontext"></property>
          <property name="newitempagetemplate"></property>
          <property name="orderby"></property>
          <property name="outputconverttablestodivs">none</property>
          <property name="outputfixattributes">True</property>
          <property name="outputfixhtml5">True</property>
          <property name="outputfixjavascript">True</property>
          <property name="outputfixlowercase">True</property>
          <property name="outputfixselfclose">True</property>
          <property name="outputresolveurls">True</property>
          <property name="partialcachedependencies">
<![CDATA[
##DEFAULT##

]]>
          </property>
          <property name="partialcacheminutes"></property>
          <property name="path">/Produkty/%</property>
          <property name="preservepartialcacheonpostback">False</property>
          <property name="selectonlypublished">True</property>
          <property name="showfordocumenttypes"></property>
          <property name="sitename"></property>
          <property name="timezonetype">inherit</property>
          <property name="useupdatepanel">False</property>
          <property name="validationerrormessage"></property>
          <property name="visible">True</property>
          <property name="webparttitle"></property>
          <property name="webparttype">ContributionList</property>
          <property name="wherecondition"></property>
        </webpart>
      </webpartzone>
      <webpartzone id="zoneRight" />
      <webpartzone id="zoneTop" />
      <webpartzone id="zoneCenter" />
    </page>
  </PageTemplateWebParts>
</cms.pagetemplate>